setup.py
mobmsg/__init__.py
mobmsg/encdec.py
mobmsg.egg-info/PKG-INFO
mobmsg.egg-info/SOURCES.txt
mobmsg.egg-info/dependency_links.txt
mobmsg.egg-info/not-zip-safe
mobmsg.egg-info/top_level.txt