Metadata-Version: 1.0
Name: mobmsg
Version: 0.2
Summary: A library for decoding the mobile messaging components(10 digits mobile number, customer id, sms id)
Home-page: https://github.com/hygull/mobmsg
Author: Rishikesh
Author-email: rishikesh0014051992@gmail.com
License: GNU GENERAL PUBLIC LICENSE, Version 3
Platform: UNKNOWN
